Workbook

Sheet Cover
B2: VAT RETURN CALCULATOR
B3: UK VAT-Registered Businesses
B6: Business Name: | C6: [Enter your business name]
B7: VAT Registration Number: | C7: [GBXXXXXXXXX]
B8: VAT Quarter: | C8: [e.g. Q1 2026 (Jan - Mar)]
B9: VAT Rate: | C9: Standard 20%
B11: WHAT THIS WORKBOOK DOES
B12: 1. Sales Sheet | C12: Record all sales invoices with auto VAT calculation
B13: 2. Purchases Sheet | C13: Record purchase invoices with VAT reclaim tracking
B14: 3. VAT Return | C14: Auto-calculates all 9 HMRC VAT Return boxes
B15: 4. Flat Rate Scheme | C15: Compares standard vs flat rate VAT schemes
B16: 5. Audit Check | C16: Validates your figures and flags any issues
B18: SHEET INDEX
B19: Sheet | C19: Description
B20: Cover | C20: This page - instructions and navigation
B21: Sales | C21: Enter your sales invoices with auto VAT @ 20%
B22: Purchases | C22: Enter your purchase invoices with reclaimable VAT
B23: VAT Return | C23: Auto-calculated HMRC VAT Return (all 9 boxes)
B24: Flat Rate | C24: Compare standard VAT vs Flat Rate Scheme
B25: Audit Check | C25: Validation formulas and error checking
B27: IMPORTANT NOTES
B28: • | C28: All calculations are formula-driven. Do not overwrite formula cells (shown in black text).
B29: • | C29: Enter your data ONLY in blue-text cells.
B30: • | C30: The VAT Return sheet auto-calculates from your Sales and Purchases entries.
B31: • | C31: Submit your VAT Return online at gov.uk by the deadline (1 month + 7 days after quarter end).
B32: • | C32: Keep all VAT invoices for at least 6 years (HMRC requirement).
B33: • | C33: Current UK VAT registration threshold: £85,000 turnover per year.

Sheet Sales
B2: SALES INVOICES
B3: Enter all sales invoices for the VAT quarter
B6: Date | C6: Invoice No | D6: Customer | E6: Description | F6: Net Amount | G6: VAT @ 20% | H6: Gross Amount
B7: 46027 | C7: INV-1001 | D7: ABC Ltd | E7: Consulting Services | F7: 2500 | G7: =F7*0.2 | H7: =F7+G7
B8: 46034 | C8: INV-1002 | D8: XYZ Ltd | E8: Website Design & Development | F8: 1800 | G8: =F8*0.2 | H8: =F8+G8
B9: 46040 | C9: INV-1003 | D9: Smith & Co | E9: Monthly Retainer - Jan | F9: 950 | G9: =F9*0.2 | H9: =F9+G9
B10: 46056 | C10: INV-1004 | D10: Green Ltd | E10: Staff Training Course | F10: 1200 | G10: =F10*0.2 | H10: =F10+G10
B11: 46068 | C11: INV-1005 | D11: ABC Ltd | E11: Additional Project Work | F11: 750 | G11: =F11*0.2 | H11: =F11+G11
B12: 46089 | C12: INV-1006 | D12: Brown & Sons | E12: Project Delivery | F12: 3200 | G12: =F12*0.2 | H12: =F12+G12
B27: TOTAL SALES | F27: =SUM(F7:F26) | G27: =SUM(G7:G26) | H27: =SUM(H7:H26)
B29: Notes:
B30: • Enter your sales invoices in the rows above. Replace the example data with your own figures.
B31: • Net Amount is the amount BEFORE VAT. VAT @ 20% and Gross Amount are calculated automatically.
B32: • Delete any unused rows before submitting your VAT return. Do not delete the TOTALS row.

Sheet Purchases
B2: PURCHASE INVOICES
B3: Enter all purchase invoices with reclaimable VAT for the quarter
B6: Date | C6: Invoice No | D6: Supplier | E6: Description | F6: Net Amount | G6: VAT @ 20% | H6: Gross Amount | I6: Reclaim?
B7: 46030 | C7: SUP-0451 | D7: Office Supplies Co | E7: Stationery & Envelopes | F7: 85.5 | G7: =F7*0.2 | H7: =F7+G7 | I7: Y
B8: 46037 | C8: SUP-0452 | D8: Vodafone Business | E8: Phone & Broadband | F8: 120 | G8: =F8*0.2 | H8: =F8+G8 | I8: Y
B9: 46044 | C9: SUP-0453 | D9: Amazon Business | E9: Laptop Computer | F9: 899 | G9: =F9*0.2 | H9: =F9+G9 | I9: Y
B10: 46058 | C10: SUP-0454 | D10: British Gas Business | E10: Electricity & Gas | F10: 245 | G10: =F10*0.2 | H10: =F10+G10 | I10: Y
B11: 46067 | C11: SUP-0455 | D11: Smith & Associates | E11: Accountancy Services | F11: 350 | G11: =F11*0.2 | H11: =F11+G11 | I11: Y
B12: 46083 | C12: SUP-0456 | D12: WeWork | E12: Office Space Rental | F12: 280 | G12: =F12*0.2 | H12: =F12+G12 | I12: Y
B27: TOTAL PURCHASES | F27: =SUM(F7:F26) | G27: =SUM(G7:G26) | H27: =SUM(H7:H26)
B29: Notes:
B30: • Enter purchase invoices above. Set 'Reclaim?' to N for non-reclaimable VAT (e.g., entertaining, cars).
B31: • You must hold a valid VAT invoice to reclaim VAT. Simplified receipts under £250 are acceptable.

Sheet VAT Return
B2: HMRC VAT RETURN
B3: All 9 boxes auto-calculated from your Sales and Purchases
B6: COMPANY INFORMATION
B7: Business Name: | C7: [Enter your business name]
B8: VAT Reg Number: | C8: [GBXXXXXXXXX]
B9: VAT Quarter: | C9: [Q1 2026 - Jan to Mar 2026]
B10: VAT Scheme: | C10: Standard Accounting (20%)
B12: OUTPUT TAX — VAT you owe on sales
B13: BOX 1 | C13: VAT due on sales and other outputs
D14: =Sales!G27
B15: BOX 2 | C15: VAT due on acquisitions from other EU countries
D16: 0
B17: BOX 3 | C17: Total VAT due (Box 1 + Box 2)
D18: =D14+D16
B20: INPUT TAX — VAT you can reclaim
B21: BOX 4 | C21: VAT reclaimed on purchases and other inputs
D22: =Purchases!G27
B24: BOX 5 | C24: NET VAT to pay or reclaim (Box 3 minus Box 4)
B25: =D18-D22
B26: =IF(D18>D22,"You owe HMRC this amount","HMRC owes you this amount")
B28: TOTAL VALUES — Excluding VAT
B29: BOX 6 | C29: Total value of sales and all other outputs (excl. VAT) | D29: =Sales!F27
B30: BOX 7 | C30: Total value of purchases and all other inputs (excl. VAT) | D30: =Purchases!F27
B31: BOX 8 | C31: Total value of EU sales (excl. VAT) | D31: 0
B32: BOX 9 | C32: Total value of EU purchases (excl. VAT) | D32: 0
B34: PAYMENT SUMMARY
B35: VAT Amount: | D35: =B25
B36: Payment Deadline: | D36: 7 May 2026
B37: Submit online at: | D37: gov.uk/vat-returns
B39: DECLARATION
B40: I confirm that the information given above is true and complete.
B41: Signed: | C41: _______________________________
B42: Date: | C42: _______________________________

Sheet Flat Rate
B2: FLAT RATE SCHEME COMPARISON
B3: See whether the Flat Rate Scheme saves you money
B6: STANDARD VAT SCHEME
B7: VAT on Sales (from VAT Return Box 1) | C7: ='VAT Return'!D14
B8: VAT on Purchases (from VAT Return Box 4) | C8: ='VAT Return'!D22
B9: NET VAT Payable under Standard Scheme | C9: ='VAT Return'!B25
B11: FLAT RATE SCHEME
B12: Your Flat Rate % (check your sector at gov.uk) | C12: 13.5
B13: Total VAT-inclusive turnover | C13: =Sales!H27
B14: VAT PAYABLE under Flat Rate | C14: =C13*(C12/100)
B16: COMPARISON
B17: Standard Scheme VAT payable | C17: =C9
B18: Flat Rate VAT payable | C18: =C14
B19: SAVING with Flat Rate | C19: =C17-C18
B20: =IF(C19>0,"Flat Rate is cheaper by this amount","Standard scheme is cheaper")
B22: Notes:
B23: • Under Flat Rate, you cannot reclaim VAT on purchases (except capital assets >£2,000)
B24: • You must leave the Flat Rate Scheme if your turnover exceeds £230,000
B25: • Common rates: IT consultancy 14.5%, retail 7.5%, hospitality 12.5%

Sheet Audit Check
B2: AUDIT CHECK & VALIDATION
B3: Automatic checks to ensure your VAT Return is accurate
B6: Check | C6: Expected | D6: Status
B7: Sales VAT = 20% of Sales Net | C7: ='VAT Return'!D14='Sales'!G27 | D7: =IF(ABS(C7)<0.01,"PASS","CHECK")
B8: Purchases VAT = 20% of Purchases Net | C8: ='VAT Return'!D22='Purchases'!G27 | D8: =IF(ABS(C8)<0.01,"PASS","CHECK")
B9: Box 3 = Box 1 + Box 2 | C9: ='VAT Return'!D18='VAT Return'!D14+'VAT Return'!D16 | D9: =IF(ABS(C9)<0.01,"PASS","CHECK")
B10: Box 5 = Box 3 - Box 4 | C10: ='VAT Return'!B25='VAT Return'!D18-'VAT Return'!D22 | D10: =IF(ABS(C10)<0.01,"PASS","CHECK")
B11: Sales Gross = Net + VAT | C11: ='Sales'!H27='Sales'!F27+'Sales'!G27 | D11: =IF(ABS(C11)<0.01,"PASS","CHECK")
B12: Purchases Gross = Net + VAT | C12: ='Purchases'!H27='Purchases'!F27+'Purchases'!G27 | D12: =IF(ABS(C12)<0.01,"PASS","CHECK")
B13: Box 6 = Total Sales (ex VAT) | C13: ='VAT Return'!D29='Sales'!F27 | D13: =IF(ABS(C13)<0.01,"PASS","CHECK")
B14: Box 7 = Total Purchases (ex VAT) | C14: ='VAT Return'!D30='Purchases'!F27 | D14: =IF(ABS(C14)<0.01,"PASS","CHECK")
B16: ALL CHECKS
B17: Checks Passed: | D17: =COUNTIF(D7:D14,"PASS")
B18: Checks Needing Attention: | D18: =COUNTIF(D7:D14,"CHECK")
B20: =IF(D18=0,"ALL CHECKS PASSED - Ready to submit","Some checks need attention - review the items above")
B22: RECONCILIATION TIPS
B23: 1. Ensure all sales invoices have been entered and none are duplicated.
B24: 2. Check that purchase invoices are dated within the correct VAT quarter.
B25: 3. Verify that VAT rates are correct (standard 20%, reduced 5%, zero 0%).
B26: 4. Reclaimable VAT must be supported by a valid VAT invoice.
B27: 5. Box 6 should match your total turnover for the quarter.
B28: 6. If Box 5 is negative, HMRC will refund you (usually within 10 days).
B29: 7. Submit online at gov.uk by the deadline to avoid penalties.
