Workbook

Sheet Cover
B1: 12-MONTH BUDGET FORECAST
B2: UK Tax Year Budget Planner (Apr - Mar)
B4: How to Use | C4: Enter budget figures in blue cells month by month.
B5: Bank Balance | C5: Opening and closing balances calculate automatically.
B6: Summary Sheet | C6: Review annual totals and key ratios.

Sheet Budget
B1: 12-MONTH BUDGET FORECAST
B3: Category | C3: Apr | D3: May | E3: Jun | F3: Jul | G3: Aug | H3: Sep | I3: Oct | J3: Nov | K3: Dec | L3: Jan | M3: Feb | N3: Mar | O3: TOTAL
B4: INCOME
B5: Product Sales | O5: =SUM(C5:N5)
B6: Service Income | O6: =SUM(C6:N6)
B7: Commission | O7: =SUM(C7:N7)
B8: Rental Income | O8: =SUM(C8:N8)
B9: Other Income | O9: =SUM(C9:N9)
B10: TOTAL INCOME | C10: =SUM(C5:C9) | D10: =SUM(D5:D9) | E10: =SUM(E5:E9) | F10: =SUM(F5:F9) | G10: =SUM(G5:G9) | H10: =SUM(H5:H9) | I10: =SUM(I5:I9) | J10: =SUM(J5:J9) | ... N10: =SUM(N5:N9) | O10: =SUM(C10:N10)
B12: EXPENSES
B13: Cost of Sales | O13: =SUM(C13:N13)
B14: Rent & Rates | O14: =SUM(C14:N14)
B15: Utilities | O15: =SUM(C15:N15)
B16: Insurance | O16: =SUM(C16:N16)
B17: Telephone & Internet | O17: =SUM(C17:N17)
B18: Office Supplies | O18: =SUM(C18:N18)
B19: Marketing | O19: =SUM(C19:N19)
B20: Travel | O20: =SUM(C20:N20)
B21: Motor Expenses | O21: =SUM(C21:N21)
B22: Professional Fees | O22: =SUM(C22:N22)
B23: Software/IT | O23: =SUM(C23:N23)
B24: Staff Costs | O24: =SUM(C24:N24)
... B28: Other | O28: =SUM(C28:N28)
B29: TOTAL EXPENSES | C29: =SUM(C13:C28) | D29: =SUM(D13:D28) | E29: =SUM(E13:E28) | F29: =SUM(F13:F28) | G29: =SUM(G13:G28) | H29: =SUM(H13:H28) | I29: =SUM(I13:I28) | J29: =SUM(J13:J28) | ... N29: =SUM(N13:N28) | O29: =SUM(C29:N29)
B30: NET PROFIT/(LOSS) | C30: =C10-C29 | D30: =D10-D29 | E30: =E10-E29 | F30: =F10-F29 | G30: =G10-G29 | H30: =H10-H29 | I30: =I10-I29 | J30: =J10-J29 | ... N30: =N10-N29 | O30: =SUM(C30:N30)
B32: OPENING BANK BALANCE | C32: 0 | D32: =C32+C30 | E32: =D32+D30 | F32: =E32+E30 | G32: =F32+F30 | H32: =G32+G30 | I32: =H32+H30 | J32: =I32+I30 | K32: =J32+J30 | ... N32: =M32+M30
B33: CLOSING BANK BALANCE | C33: =C32+C30 | D33: =D32+D30 | E33: =E32+E30 | F33: =F32+F30 | G33: =G32+G30 | H33: =H32+H30 | I33: =I32+I30 | J33: =J32+J30 | ... N33: =N32+N30

Sheet Summary
B1: BUDGET SUMMARY & RATIOS
B3: Metric | C3: Value | D3: Notes
B4: Total Budgeted Income | C4: ='Budget'!O10 | D4: All income sources
B5: Total Budgeted Expenses | C5: ='Budget'!O29 | D5: All business costs
B6: Net Budgeted Profit | C6: ='Budget'!O30 | D6: Income minus expenses
B7: Profit Margin | C7: =IF(C4>0,C6/C4,0) | D7: Net profit as % of income
B9: Highest Monthly Income | C9: =MAX('Budget'!C4:N4) | D9: Best month
B10: Lowest Monthly Income | C10: =MIN('Budget'!C4:N4) | D10: Quietest month
B12: Opening Balance (Apr) | C12: ='Budget'!C32 | D12: Starting bank balance
B13: Closing Balance (Mar) | C13: ='Budget'!O33 | D13: Projected year-end balance
B14: Average Monthly Profit | C14: =C6/12 | D14: Spread across the year
