Workbook

Sheet Cover
B2: RENTAL PROPERTY INCOME & EXPENSES
B3: For UK Landlords — Up to 5 Properties
B6: LANDLORD INFORMATION
B7: Name: | C7: [Enter landlord name]
B8: Tax Year: | C8: 2025/26 (6 April 2025 — 5 April 2026)
B9: UTR (Unique Tax Reference): | C9: [Enter your 10-digit UTR]
B10: Number of Properties: | C10: [Enter number]
B12: WHAT THIS WORKBOOK DOES
B13: 1. Properties | C13: Record details for up to 5 rental properties
B14: 2. Income | C14: Track monthly rental income per property
B15: 3. Expenses | C15: Log all property-related expenses by category
B16: 4. Annual Summary | C16: Auto-calculates profit/loss per property and total
B17: 5. Tax Workings | C17: Mortgage interest relief, taxable profit, tax estimate
B19: SHEET INDEX
B20: Sheet | C20: Description
B21: Cover | C21: This page — instructions and navigation
B22: Properties | C22: Details for up to 5 rental properties
B23: Income | C23: Monthly rent received per property
B24: Expenses | C24: Property expenses by category
B25: Annual Summary | C25: Profit/loss per property and in total
B26: Tax Workings | C26: Mortgage relief, taxable profit, tax estimate
B28: IMPORTANT NOTES
B29: • | C29: Section 24: Mortgage interest is NOT deductible as an expense. You receive a 20% tax credit instead.
B30: • | C30: Wear & Tear allowance has been abolished. Use Replacement Relief for replacing furnishings only.
B31: • | C31: Keep all receipts, invoices and bank statements for at least 5 years.
B32: • | C32: Report property income on the UK Property pages of your Self Assessment tax return.
B33: • | C33: If you let a room in your own home, you may qualify for the Rent a Room Scheme (£7,500 allowance).

Sheet Properties
B2: PROPERTY DETAILS
B3: Enter details for each rental property
B6: Property | C6: Address | D6: Postcode | E6: Purchase Date | F6: Purchase Price | G6: Current Value | H6: Mortgage Lender | I6: Monthly Payment
B7: Flat 1 | C7: 12 High Street, London | D7: W1A 1AA | E7: 43174 | F7: 285000 | G7: 340000 | H7: Nationwide BS | I7: 850
B8: Flat 2 | C8: 3 Oak Avenue, Manchester | D8: M1 1AA | E8: 43699 | F8: 175000 | G8: 195000 | H8: Halifax | I8: 520
B9: House 1
B10: House 2
B11: House 3
B12: TOTAL PORTFOLIO VALUE | F12: =SUM(F7:F11) | G12: =SUM(G7:G11) | I12: =SUM(I7:I11)

Sheet Income
B2: RENTAL INCOME
B3: Record monthly rent received for each property
B5: Month | C5: =Properties!B7 | D5: =Properties!B8 | E5: =Properties!B9 | F5: =Properties!B10 | G5: TOTAL
B6: April | C6: 1200 | D6: 850 | G6: =SUM(C6:F6)
B7: May | C7: 1200 | D7: 850 | G7: =SUM(C7:F7)
B8: June | C8: 1200 | D8: 850 | G8: =SUM(C8:F8)
B9: July | C9: 1200 | D9: 850 | G9: =SUM(C9:F9)
B10: August | C10: 1200 | D10: 850 | G10: =SUM(C10:F10)
B11: September | C11: 1200 | D11: 850 | G11: =SUM(C11:F11)
B12: October | C12: 1200 | D12: 850 | G12: =SUM(C12:F12)
B13: November | C13: 1200 | D13: 850 | G13: =SUM(C13:F13)
B14: December | C14: 1200 | D14: 850 | G14: =SUM(C14:F14)
B15: January | C15: 1200 | D15: 850 | G15: =SUM(C15:F15)
B16: February | C16: 1200 | D16: 850 | G16: =SUM(C16:F16)
B17: March | C17: 1200 | D17: 850 | G17: =SUM(C17:F17)
B18: TOTAL | C18: =SUM(C6:C17) | D18: =SUM(D6:D17) | E18: =SUM(E6:E17) | F18: =SUM(F6:F17) | G18: =SUM(G6:G17)

Sheet Expenses
B2: PROPERTY EXPENSES
B3: Log all property-related expenses throughout the tax year
B6: Date | C6: Property | D6: Category | E6: Description | F6: Amount
B7: 45748 | C7: Flat 1 | D7: Agent Fees | E7: Letting agent commission (10%) | F7: 120
B8: 45750 | C8: Flat 1 | D8: Insurance | E8: Buildings insurance (monthly) | F8: 45
B9: 45752 | C9: Flat 1 | D9: Repairs | E9: Plumber - leak repair | F9: 185
B10: 45757 | C10: Flat 2 | D10: Council Tax | E10: Council tax | F10: 145
B11: 45759 | C11: Flat 2 | D11: Safety Certs | E11: Gas safety certificate | F11: 65
B12: 45762 | C12: Flat 1 | D12: Mortgage Interest | E12: Mortgage interest payment | F12: 420
B13: 45762 | C13: Flat 2 | D13: Mortgage Interest | E13: Mortgage interest payment | F13: 260
B14: 45778 | C14: Flat 1 | D14: Agent Fees | E14: Letting agent commission (10%) | F14: 120
B15: 45780 | C15: Flat 1 | D15: Insurance | E15: Buildings insurance (monthly) | F15: 45
B16: 45787 | C16: Flat 2 | D16: Council Tax | E16: Council tax | F16: 145
B41: TOTAL EXPENSES | F41: =SUM(F7:F40)
B43: EXPENSE BREAKDOWN BY CATEGORY
B44: Category | C44: Description | F44: Total
B45: Agent Fees | C45: Letting agent commission and management fees | F45: =SUMIF($D$7:$D$40,B45,$F$7:$F$40)
B46: Insurance | C46: Buildings, contents and landlord insurance | F46: =SUMIF($D$7:$D$40,B46,$F$7:$F$40)
B47: Repairs | C47: Repairs, maintenance and decoration | F47: =SUMIF($D$7:$D$40,B47,$F$7:$F$40)
B48: Council Tax | C48: Council tax on rental properties | F48: =SUMIF($D$7:$D$40,B48,$F$7:$F$40)
B49: Utilities | C49: Gas, electricity, water and sewerage | F49: =SUMIF($D$7:$D$40,B49,$F$7:$F$40)
B50: Safety Certs | C50: Gas safety, EPC, electrical checks | F50: =SUMIF($D$7:$D$40,B50,$F$7:$F$40)
B51: Cleaning | C51: Cleaning and gardening services | F51: =SUMIF($D$7:$D$40,B51,$F$7:$F$40)
B52: Legal | C52: Legal fees and accountancy | F52: =SUMIF($D$7:$D$40,B52,$F$7:$F$40)
B53: Advertising | C53: Advertising for tenants | F53: =SUMIF($D$7:$D$40,B53,$F$7:$F$40)
B54: Mortgage Interest | C54: Interest only (not capital repayments) | F54: =SUMIF($D$7:$D$40,B54,$F$7:$F$40)
B55: Other | C55: Any other property-related expenses | F55: =SUMIF($D$7:$D$40,B55,$F$7:$F$40)

Sheet Annual Summary
B2: ANNUAL SUMMARY
B3: Profit and loss per property — auto-calculated
B6: Category | C6: =Properties!B7 | D6: =Properties!B8 | E6: =Properties!B9 | F6: =Properties!B10 | G6: TOTAL
B7: INCOME
B8: Rental Income | C8: =Income!C18 | D8: =Income!D18 | E8: =Income!E18 | F8: =Income!F18 | G8: =SUM(C8:F8)
B10: EXPENSES
B11: Agent Fees | C11: =SUMIFS(Expenses!$F$7:$F$40,Expenses!$C$7:$C$40,Properties!B7,Expenses!$D$7:$D$40,$B11) | D11: =SUMIFS(Expenses!$F$7:$F$40,Expenses!$C$7:$C$40,Properties!B8,Expenses!$D$7:$D$40,$B11) | E11: =SUMIFS(Expenses!$F$7:$F$40,Expenses!$C$7:$C$40,Properties!B9,Expenses!$D$7:$D$40,$B11) | F11: =SUMIFS(Expenses!$F$7:$F$40,Expenses!$C$7:$C$40,Properties!B10,Expenses!$D$7:$D$40,$B11) | G11: =SUM(C11:F11)
B12: Insurance | C12: =SUMIFS(Expenses!$F$7:$F$40,Expenses!$C$7:$C$40,Properties!B7,Expenses!$D$7:$D$40,$B12) | D12: =SUMIFS(Expenses!$F$7:$F$40,Expenses!$C$7:$C$40,Properties!B8,Expenses!$D$7:$D$40,$B12) | E12: =SUMIFS(Expenses!$F$7:$F$40,Expenses!$C$7:$C$40,Properties!B9,Expenses!$D$7:$D$40,$B12) | F12: =SUMIFS(Expenses!$F$7:$F$40,Expenses!$C$7:$C$40,Properties!B10,Expenses!$D$7:$D$40,$B12) | G12: =SUM(C12:F12)
B13: Repairs | C13: =SUMIFS(Expenses!$F$7:$F$40,Expenses!$C$7:$C$40,Properties!B7,Expenses!$D$7:$D$40,$B13) | D13: =SUMIFS(Expenses!$F$7:$F$40,Expenses!$C$7:$C$40,Properties!B8,Expenses!$D$7:$D$40,$B13) | E13: =SUMIFS(Expenses!$F$7:$F$40,Expenses!$C$7:$C$40,Properties!B9,Expenses!$D$7:$D$40,$B13) | F13: =SUMIFS(Expenses!$F$7:$F$40,Expenses!$C$7:$C$40,Properties!B10,Expenses!$D$7:$D$40,$B13) | G13: =SUM(C13:F13)
B14: Council Tax | C14: =SUMIFS(Expenses!$F$7:$F$40,Expenses!$C$7:$C$40,Properties!B7,Expenses!$D$7:$D$40,$B14) | D14: =SUMIFS(Expenses!$F$7:$F$40,Expenses!$C$7:$C$40,Properties!B8,Expenses!$D$7:$D$40,$B14) | E14: =SUMIFS(Expenses!$F$7:$F$40,Expenses!$C$7:$C$40,Properties!B9,Expenses!$D$7:$D$40,$B14) | F14: =SUMIFS(Expenses!$F$7:$F$40,Expenses!$C$7:$C$40,Properties!B10,Expenses!$D$7:$D$40,$B14) | G14: =SUM(C14:F14)
B15: Utilities | C15: =SUMIFS(Expenses!$F$7:$F$40,Expenses!$C$7:$C$40,Properties!B7,Expenses!$D$7:$D$40,$B15) | D15: =SUMIFS(Expenses!$F$7:$F$40,Expenses!$C$7:$C$40,Properties!B8,Expenses!$D$7:$D$40,$B15) | E15: =SUMIFS(Expenses!$F$7:$F$40,Expenses!$C$7:$C$40,Properties!B9,Expenses!$D$7:$D$40,$B15) | F15: =SUMIFS(Expenses!$F$7:$F$40,Expenses!$C$7:$C$40,Properties!B10,Expenses!$D$7:$D$40,$B15) | G15: =SUM(C15:F15)
B16: Safety Certs | C16: =SUMIFS(Expenses!$F$7:$F$40,Expenses!$C$7:$C$40,Properties!B7,Expenses!$D$7:$D$40,$B16) | D16: =SUMIFS(Expenses!$F$7:$F$40,Expenses!$C$7:$C$40,Properties!B8,Expenses!$D$7:$D$40,$B16) | E16: =SUMIFS(Expenses!$F$7:$F$40,Expenses!$C$7:$C$40,Properties!B9,Expenses!$D$7:$D$40,$B16) | F16: =SUMIFS(Expenses!$F$7:$F$40,Expenses!$C$7:$C$40,Properties!B10,Expenses!$D$7:$D$40,$B16) | G16: =SUM(C16:F16)
B17: Cleaning | C17: =SUMIFS(Expenses!$F$7:$F$40,Expenses!$C$7:$C$40,Properties!B7,Expenses!$D$7:$D$40,$B17) | D17: =SUMIFS(Expenses!$F$7:$F$40,Expenses!$C$7:$C$40,Properties!B8,Expenses!$D$7:$D$40,$B17) | E17: =SUMIFS(Expenses!$F$7:$F$40,Expenses!$C$7:$C$40,Properties!B9,Expenses!$D$7:$D$40,$B17) | F17: =SUMIFS(Expenses!$F$7:$F$40,Expenses!$C$7:$C$40,Properties!B10,Expenses!$D$7:$D$40,$B17) | G17: =SUM(C17:F17)
B18: Legal | C18: =SUMIFS(Expenses!$F$7:$F$40,Expenses!$C$7:$C$40,Properties!B7,Expenses!$D$7:$D$40,$B18) | D18: =SUMIFS(Expenses!$F$7:$F$40,Expenses!$C$7:$C$40,Properties!B8,Expenses!$D$7:$D$40,$B18) | E18: =SUMIFS(Expenses!$F$7:$F$40,Expenses!$C$7:$C$40,Properties!B9,Expenses!$D$7:$D$40,$B18) | F18: =SUMIFS(Expenses!$F$7:$F$40,Expenses!$C$7:$C$40,Properties!B10,Expenses!$D$7:$D$40,$B18) | G18: =SUM(C18:F18)
B19: Advertising | C19: =SUMIFS(Expenses!$F$7:$F$40,Expenses!$C$7:$C$40,Properties!B7,Expenses!$D$7:$D$40,$B19) | D19: =SUMIFS(Expenses!$F$7:$F$40,Expenses!$C$7:$C$40,Properties!B8,Expenses!$D$7:$D$40,$B19) | E19: =SUMIFS(Expenses!$F$7:$F$40,Expenses!$C$7:$C$40,Properties!B9,Expenses!$D$7:$D$40,$B19) | F19: =SUMIFS(Expenses!$F$7:$F$40,Expenses!$C$7:$C$40,Properties!B10,Expenses!$D$7:$D$40,$B19) | G19: =SUM(C19:F19)
B20: Mortgage Interest | C20: =SUMIFS(Expenses!$F$7:$F$40,Expenses!$C$7:$C$40,Properties!B7,Expenses!$D$7:$D$40,$B20) | D20: =SUMIFS(Expenses!$F$7:$F$40,Expenses!$C$7:$C$40,Properties!B8,Expenses!$D$7:$D$40,$B20) | E20: =SUMIFS(Expenses!$F$7:$F$40,Expenses!$C$7:$C$40,Properties!B9,Expenses!$D$7:$D$40,$B20) | F20: =SUMIFS(Expenses!$F$7:$F$40,Expenses!$C$7:$C$40,Properties!B10,Expenses!$D$7:$D$40,$B20) | G20: =SUM(C20:F20)
B21: Other | C21: =SUMIFS(Expenses!$F$7:$F$40,Expenses!$C$7:$C$40,Properties!B7,Expenses!$D$7:$D$40,$B21) | D21: =SUMIFS(Expenses!$F$7:$F$40,Expenses!$C$7:$C$40,Properties!B8,Expenses!$D$7:$D$40,$B21) | E21: =SUMIFS(Expenses!$F$7:$F$40,Expenses!$C$7:$C$40,Properties!B9,Expenses!$D$7:$D$40,$B21) | F21: =SUMIFS(Expenses!$F$7:$F$40,Expenses!$C$7:$C$40,Properties!B10,Expenses!$D$7:$D$40,$B21) | G21: =SUM(C21:F21)
B22: TOTAL EXPENSES | C22: =SUM(C11:C21) | D22: =SUM(D11:D21) | E22: =SUM(E11:E21) | F22: =SUM(F11:F21) | G22: =SUM(G11:G21)
B24: NET PROFIT / (LOSS) | C24: =C8-C22 | D24: =D8-D22 | E24: =E8-E22 | F24: =F8-F22 | G24: =G8-G22
C25: =IF(G24>=0,"Portfolio is profitable","Portfolio is making a loss — review expenses")

Sheet Tax Workings
B2: TAX WORKINGS
B3: Mortgage interest relief, taxable profit and tax estimate
C6: =Properties!B7 | D6: =Properties!B8 | E6: =Properties!B9 | F6: =Properties!B10
B7: PROFIT CALCULATION
B8: Rental Income | C8: ='Annual Summary'!C8 | D8: ='Annual Summary'!D8 | E8: ='Annual Summary'!E8 | F8: ='Annual Summary'!F8
B9: Less: Allowable Expenses (excl. mortgage interest) | C9: ='Annual Summary'!C22-'Annual Summary'!C20 | D9: ='Annual Summary'!D22-'Annual Summary'!D20 | E9: ='Annual Summary'!E22-'Annual Summary'!E20 | F9: ='Annual Summary'!F22-'Annual Summary'!F20
B10: Less: Mortgage Interest | C10: ='Annual Summary'!C20 | D10: ='Annual Summary'!D20 | E10: ='Annual Summary'!E20 | F10: ='Annual Summary'!F20
B11: TAXABLE PROFIT / (LOSS) | C11: =C8-C9-C10 | D11: =D8-D9-D10 | E11: =E8-E9-E10 | F11: =F8-F9-F10
B13: MORTGAGE INTEREST TAX RELIEF (Section 24)
B14: Mortgage Interest Paid | D14: =SUM(C10:F10)
B15: Tax Credit at 20% (basic rate) | D15: =D14*0.2
B17: TAX CALCULATION
B18: Total Taxable Profit | D18: =SUM(C11:F11)
B19: Personal Allowance (2025/26) | D19: 12570
B20: Taxable Amount (profit less allowance) | D20: =MAX(D18-D19,0)
B21: Tax at Basic Rate (20%) | D21: =D20*0.2
B22: Less: Mortgage Interest Tax Credit | D22: =D15
B23: ESTIMATED TAX PAYABLE | D23: =MAX(D21-D22,0)
B24: Effective Tax Rate on Profit | D24: =IF(D18>0,D23/D18,0)
B26: IMPORTANT TAX NOTES
B27: Section 24 (Finance Act 2015): Mortgage interest is NOT an allowable expense. You get a 20% tax credit instead.
B28: Wear & Tear Allowance was abolished in April 2016. Use Replacement Relief for replacing furnishings only.
B29: These calculations assume all profit falls within the basic rate band. Higher rate taxpayers pay 40%.
B30: You may also pay Class 2 NIC (£3.45/week) and Class 4 NIC (9% of profits between £12,570-£50,270).
B31: Report this income on the UK Property pages of your Self Assessment (SA105 supplementary pages).
B32: Submission deadline: 31 January 2027 (for the 2025/26 tax year).
